NaturalLanguageProcessingLectureNotesColumbiaCs4705/README.md
NaturalLanguageProcessingLectureNotesColumbiaCs4705/__init__.py
NaturalLanguageProcessingLectureNotesColumbiaCs4705/__main__.py
NaturalLanguageProcessingLectureNotesColumbiaCs4705/file.pdf
NaturalLanguageProcessingLectureNotesColumbiaCs4705/index.html
natural_language_processing_lecture_notes_columbia_cs4705-2024.3.2.0.dist-info/METADATA
natural_language_processing_lecture_notes_columbia_cs4705-2024.3.2.0.dist-info/WHEEL
natural_language_processing_lecture_notes_columbia_cs4705-2024.3.2.0.dist-info/entry_points.txt
natural_language_processing_lecture_notes_columbia_cs4705-2024.3.2.0.dist-info/top_level.txt
natural_language_processing_lecture_notes_columbia_cs4705-2024.3.2.0.dist-info/RECORD
